tapioca_toggl/__init__.py
tapioca_toggl/resource_mapping.py
tapioca_toggl/tapioca_toggl.py
tapioca_toggl-0.1.0.dist-info/DESCRIPTION.rst
tapioca_toggl-0.1.0.dist-info/METADATA
tapioca_toggl-0.1.0.dist-info/metadata.json
tapioca_toggl-0.1.0.dist-info/RECORD
tapioca_toggl-0.1.0.dist-info/top_level.txt
tapioca_toggl-0.1.0.dist-info/WHEEL
