Metadata-Version: 2.0
Name: tapioca-toggl
Version: 0.1.0
Summary: Python wrapper for Toggl API v8
Home-page: https://github.com/hackebrot/tapioca-toggl
Author: Raphael Pierzina
Author-email: raphael@hackebrot.de
License: MIT
Keywords: toggl,api-wrapper
Platform: UNKNOWN
Classifier: Development Status :: 3 - Alpha
Classifier: Intended Audience :: Developers
Classifier: License :: OSI Approved :: MIT License
Classifier: Natural Language :: English
Classifier: Operating System :: OS Independent
Classifier: Programming Language :: Python :: 2
Classifier: Programming Language :: Python :: 2.7
Classifier: Programming Language :: Python :: 3
Classifier: Programming Language :: Python :: 3.3
Classifier: Programming Language :: Python :: 3.4
Classifier: Programming Language :: Python :: 3.5
Classifier: Programming Language :: Python :: Implementation :: CPython
Classifier: Programming Language :: Python
Requires-Dist: tapioca-wrapper
